{"jobicon":1,"skills":{"1032":{"type":0,"nameid":0,"maxlevel":1,"levels":[{"required_level":34,"mpcost":16,"explanationid":38,"spcost":0,"cd":10000,"explanationparams":["20","180"],"pvp_explanationparams":["10","180"],"pvp_explanationid":38,"pvp_cd":10000,"pvp_mpcost":8}],"image":"02","icon":57,"needweapon":[],"requires":[],"sp_requires":[0,0]},"1001":{"type":0,"nameid":1,"maxlevel":29,"levels":[{"required_level":1,"mpcost":12,"explanationid":19,"spcost":0,"cd":5000,"explanationparams":["67","2"],"pvp_explanationparams":["34","1"],"pvp_explanationid":19,"pvp_cd":4500,"pvp_mpcost":7},{"required_level":4,"mpcost":15,"explanationid":19,"spcost":1,"cd":5000,"explanationparams":["69","4"],"pvp_explanationparams":["35","2"],"pvp_explanationid":19,"pvp_cd":4500,"pvp_mpcost":8},{"required_level":7,"mpcost":17,"explanationid":19,"spcost":1,"cd":5000,"explanationparams":["71","9"],"pvp_explanationparams":["36","3"],"pvp_explanationid":19,"pvp_cd":4500,"pvp_mpcost":9},{"required_level":10,"mpcost":20,"explanationid":19,"spcost":1,"cd":5000,"explanationparams":["73","13"],"pvp_explanationparams":["37","4"],"pvp_explanationid":19,"pvp_cd":4500,"pvp_mpcost":10},{"required_level":13,"mpcost":22,"explanationid":19,"spcost":1,"cd":5000,"explanationparams":["75","21"],"pvp_explanationparams":["38","5"],"pvp_explanationid":19,"pvp_cd":4500,"pvp_mpcost":12},{"required_level":16,"mpcost":25,"explanationid":19,"spcost":1,"cd":5000,"explanationparams":["83","40"],"pvp_explanationparams":["42","6"],"pvp_explanationid":19,"pvp_cd":4500,"pvp_mpcost":13},{"required_level":19,"mpcost":27,"explanationid":19,"spcost":1,"cd":5000,"explanationparams":["85","48"],"pvp_explanationparams":["43","7"],"pvp_explanationid":19,"pvp_cd":4500,"pvp_mpcost":14},{"required_level":22,"mpcost":30,"explanationid":19,"spcost":1,"cd":5000,"explanationparams":["87","68"],"pvp_explanationparams":["44","8"],"pvp_explanationid":19,"pvp_cd":4500,"pvp_mpcost":15},{"required_level":25,"mpcost":32,"explanationid":19,"spcost":1,"cd":5000,"explanationparams":["89","180"],"pvp_explanationparams":["45","14"],"pvp_explanationid":19,"pvp_cd":4500,"pvp_mpcost":17},{"required_level":28,"mpcost":35,"explanationid":19,"spcost":1,"cd":5000,"explanationparams":["90","206"],"pvp_explanationparams":["46","16"],"pvp_explanationid":19,"pvp_cd":4500,"pvp_mpcost":18},{"required_level":31,"mpcost":37,"explanationid":19,"spcost":1,"cd":5000,"explanationparams":["99","280"],"pvp_explanationparams":["49","22"],"pvp_explanationid":19,"pvp_cd":4500,"pvp_mpcost":19},{"required_level":34,"mpcost":39,"explanationid":19,"spcost":1,"cd":5000,"explanationparams":["101","708"],"pvp_explanationparams":["50","57"],"pvp_explanationid":19,"pvp_cd":4500,"pvp_mpcost":20},{"required_level":37,"mpcost":42,"explanationid":19,"spcost":1,"cd":5000,"explanationparams":["102","849"],"pvp_explanationparams":["51","68"],"pvp_explanationid":19,"pvp_cd":4500,"pvp_mpcost":21},{"required_level":40,"mpcost":44,"explanationid":19,"spcost":1,"cd":5000,"explanationparams":["104","1007"],"pvp_explanationparams":["52","81"],"pvp_explanationid":19,"pvp_cd":4500,"pvp_mpcost":23},{"required_level":43,"mpcost":46,"explanationid":19,"spcost":1,"cd":5000,"explanationparams":["106","2091"],"pvp_explanationparams":["53","167"],"pvp_explanationid":19,"pvp_cd":4500,"pvp_mpcost":24},{"required_level":46,"mpcost":49,"explanationid":19,"spcost":1,"cd":5000,"explanationparams":["115","3115"],"pvp_explanationparams":["57","249"],"pvp_explanationid":19,"pvp_cd":4500,"pvp_mpcost":25},{"required_level":49,"mpcost":52,"explanationid":19,"spcost":1,"cd":5000,"explanationparams":["116","3509"],"pvp_explanationparams":["58","281"],"pvp_explanationid":19,"pvp_cd":4500,"pvp_mpcost":26},{"required_level":52,"mpcost":54,"explanationid":19,"spcost":1,"cd":5000,"explanationparams":["118","3909"],"pvp_explanationparams":["59","313"],"pvp_explanationid":19,"pvp_cd":4500,"pvp_mpcost":27},{"required_level":55,"mpcost":56,"explanationid":19,"spcost":1,"cd":5000,"explanationparams":["120","4316"],"pvp_explanationparams":["60","345"],"pvp_explanationid":19,"pvp_cd":4500,"pvp_mpcost":29},{"required_level":58,"mpcost":59,"explanationid":19,"spcost":1,"cd":5000,"explanationparams":["122","4730"],"pvp_explanationparams":["61","378"],"pvp_explanationid":19,"pvp_cd":4500,"pvp_mpcost":30},{"required_level":61,"mpcost":61,"explanationid":19,"spcost":1,"cd":5000,"explanationparams":["130","5937"],"pvp_explanationparams":["65","475"],"pvp_explanationid":19,"pvp_cd":4500,"pvp_mpcost":31},{"required_level":64,"mpcost":64,"explanationid":19,"spcost":1,"cd":5000,"explanationparams":["132","6024"],"pvp_explanationparams":["66","482"],"pvp_explanationid":19,"pvp_cd":4500,"pvp_mpcost":32},{"required_level":67,"mpcost":66,"explanationid":19,"spcost":1,"cd":5000,"explanationparams":["134","6115"],"pvp_explanationparams":["67","489"],"pvp_explanationid":19,"pvp_cd":4500,"pvp_mpcost":34},{"required_level":70,"mpcost":68,"explanationid":19,"spcost":1,"cd":5000,"explanationparams":["136","6210"],"pvp_explanationparams":["68","497"],"pvp_explanationid":19,"pvp_cd":4500,"pvp_mpcost":35},{"required_level":73,"mpcost":71,"explanationid":19,"spcost":1,"cd":5000,"explanationparams":["137","6308"],"pvp_explanationparams":["69","505"],"pvp_explanationid":19,"pvp_cd":4500,"pvp_mpcost":36},{"required_level":76,"mpcost":73,"explanationid":19,"spcost":1,"cd":5000,"explanationparams":["146","7317"],"pvp_explanationparams":["73","585"],"pvp_explanationid":19,"pvp_cd":4500,"pvp_mpcost":37},{"required_level":79,"mpcost":76,"explanationid":19,"spcost":1,"cd":5000,"explanationparams":["148","7423"],"pvp_explanationparams":["74","594"],"pvp_explanationid":19,"pvp_cd":4500,"pvp_mpcost":38},{"required_level":82,"mpcost":78,"explanationid":19,"spcost":1,"cd":5000,"explanationparams":["149","7533"],"pvp_explanationparams":["75","603"],"pvp_explanationid":19,"pvp_cd":4500,"pvp_mpcost":40},{"required_level":85,"mpcost":81,"explanationid":19,"spcost":1,"cd":5000,"explanationparams":["151","7646"],"pvp_explanationparams":["76","612"],"pvp_explanationid":19,"pvp_cd":4500,"pvp_mpcost":41}],"image":"02","icon":0,"needweapon":[],"requires":[],"sp_requires":[0,0]},"1003":{"type":0,"nameid":2,"maxlevel":28,"levels":[{"required_level":3,"mpcost":13,"explanationid":20,"spcost":3,"cd":14000,"explanationparams":["20","1"],"pvp_explanationparams":["12","1"],"pvp_explanationid":20,"pvp_cd":28000,"pvp_mpcost":7},{"required_level":6,"mpcost":15,"explanationid":20,"spcost":1,"cd":14000,"explanationparams":["21","3"],"pvp_explanationparams":["13","1"],"pvp_explanationid":20,"pvp_cd":28000,"pvp_mpcost":8},{"required_level":9,"mpcost":18,"explanationid":20,"spcost":1,"cd":14000,"explanationparams":["21","6"],"pvp_explanationparams":["14","2"],"pvp_explanationid":20,"pvp_cd":28000,"pvp_mpcost":9},{"required_level":12,"mpcost":20,"explanationid":20,"spcost":1,"cd":14000,"explanationparams":["22","9"],"pvp_explanationparams":["14","4"],"pvp_explanationid":20,"pvp_cd":28000,"pvp_mpcost":11},{"required_level":15,"mpcost":23,"explanationid":20,"spcost":1,"cd":14000,"explanationparams":["23","12"],"pvp_explanationparams":["15","5"],"pvp_explanationid":20,"pvp_cd":28000,"pvp_mpcost":12},{"required_level":18,"mpcost":25,"explanationid":20,"spcost":1,"cd":14000,"explanationparams":["29","20"],"pvp_explanationparams":["18","8"],"pvp_explanationid":20,"pvp_cd":28000,"pvp_mpcost":13},{"required_level":21,"mpcost":28,"explanationid":20,"spcost":1,"cd":14000,"explanationparams":["30","27"],"pvp_explanationparams":["19","11"],"pvp_explanationid":20,"pvp_cd":28000,"pvp_mpcost":15},{"required_level":24,"mpcost":31,"explanationid":20,"spcost":1,"cd":14000,"explanationparams":["31","32"],"pvp_explanationparams":["19","28"],"pvp_explanationid":20,"pvp_cd":28000,"pvp_mpcost":16},{"required_level":27,"mpcost":33,"explanationid":20,"spcost":1,"cd":14000,"explanationparams":["32","83"],"pvp_explanationparams":["20","34"],"pvp_explanationid":20,"pvp_cd":28000,"pvp_mpcost":17},{"required_level":30,"mpcost":36,"explanationid":20,"spcost":1,"cd":14000,"explanationparams":["33","97"],"pvp_explanationparams":["21","39"],"pvp_explanationid":20,"pvp_cd":28000,"pvp_mpcost":18},{"required_level":33,"mpcost":38,"explanationid":20,"spcost":1,"cd":14000,"explanationparams":["38","240"],"pvp_explanationparams":["24","100"],"pvp_explanationid":20,"pvp_cd":28000,"pvp_mpcost":19},{"required_level":36,"mpcost":40,"explanationid":20,"spcost":1,"cd":14000,"explanationparams":["39","287"],"pvp_explanationparams":["25","119"],"pvp_explanationid":20,"pvp_cd":28000,"pvp_mpcost":21},{"required_level":39,"mpcost":42,"explanationid":20,"spcost":1,"cd":14000,"explanationparams":["40","340"],"pvp_explanationparams":["25","140"],"pvp_explanationid":20,"pvp_cd":28000,"pvp_mpcost":22},{"required_level":42,"mpcost":45,"explanationid":20,"spcost":1,"cd":14000,"explanationparams":["41","691"],"pvp_explanationparams":["26","284"],"pvp_explanationid":20,"pvp_cd":28000,"pvp_mpcost":23},{"required_level":45,"mpcost":47,"explanationid":20,"spcost":1,"cd":14000,"explanationparams":["42","790"],"pvp_explanationparams":["27","340"],"pvp_explanationid":20,"pvp_cd":28000,"pvp_mpcost":24},{"required_level":48,"mpcost":50,"explanationid":20,"spcost":1,"cd":14000,"explanationparams":["48","1112"],"pvp_explanationparams":["30","456"],"pvp_explanationid":20,"pvp_cd":28000,"pvp_mpcost":26},{"required_level":51,"mpcost":52,"explanationid":20,"spcost":1,"cd":14000,"explanationparams":["49","1244"],"pvp_explanationparams":["31","509"],"pvp_explanationid":20,"pvp_cd":28000,"pvp_mpcost":27},{"required_level":54,"mpcost":55,"explanationid":20,"spcost":1,"cd":14000,"explanationparams":["50","1379"],"pvp_explanationparams":["31","563"],"pvp_explanationid":20,"pvp_cd":28000,"pvp_mpcost":28},{"required_level":57,"mpcost":57,"explanationid":20,"spcost":1,"cd":14000,"explanationparams":["51","1518"],"pvp_explanationparams":["32","619"],"pvp_explanationid":20,"pvp_cd":28000,"pvp_mpcost":29},{"required_level":60,"mpcost":59,"explanationid":20,"spcost":1,"cd":14000,"explanationparams":["52","1660"],"pvp_explanationparams":["32","664"],"pvp_explanationid":20,"pvp_cd":28000,"pvp_mpcost":30},{"required_level":63,"mpcost":62,"explanationid":20,"spcost":1,"cd":14000,"explanationparams":["57","1977"],"pvp_explanationparams":["36","791"],"pvp_explanationid":20,"pvp_cd":28000,"pvp_mpcost":32},{"required_level":66,"mpcost":65,"explanationid":20,"spcost":1,"cd":14000,"explanationparams":["58","2039"],"pvp_explanationparams":["37","816"],"pvp_explanationid":20,"pvp_cd":28000,"pvp_mpcost":33},{"required_level":69,"mpcost":67,"explanationid":20,"spcost":1,"cd":14000,"explanationparams":["59","2104"],"pvp_explanationparams":["37","842"],"pvp_explanationid":20,"pvp_cd":28000,"pvp_mpcost":34},{"required_level":72,"mpcost":69,"explanationid":20,"spcost":1,"cd":14000,"explanationparams":["60","2171"],"pvp_explanationparams":["38","869"],"pvp_explanationid":20,"pvp_cd":28000,"pvp_mpcost":35},{"required_level":75,"mpcost":72,"explanationid":20,"spcost":1,"cd":14000,"explanationparams":["61","2241"],"pvp_explanationparams":["38","897"],"pvp_explanationid":20,"pvp_cd":28000,"pvp_mpcost":36},{"required_level":78,"mpcost":75,"explanationid":20,"spcost":1,"cd":14000,"explanationparams":["67","2574"],"pvp_explanationparams":["42","1030"],"pvp_explanationid":20,"pvp_cd":28000,"pvp_mpcost":38},{"required_level":81,"mpcost":77,"explanationid":20,"spcost":1,"cd":14000,"explanationparams":["68","2649"],"pvp_explanationparams":["42","1060"],"pvp_explanationid":20,"pvp_cd":28000,"pvp_mpcost":39},{"required_level":84,"mpcost":80,"explanationid":20,"spcost":1,"cd":14000,"explanationparams":["69","2728"],"pvp_explanationparams":["43","1092"],"pvp_explanationid":20,"pvp_cd":28000,"pvp_mpcost":40}],"image":"02","icon":1,"needweapon":[],"requires":[],"sp_requires":[0,0]},"1008":{"type":0,"nameid":3,"maxlevel":18,"levels":[{"required_level":1,"mpcost":12,"explanationid":21,"spcost":0,"cd":10000,"explanationparams":["107","5","6"],"pvp_explanationparams":["67","3","6"],"pvp_explanationid":39,"pvp_cd":12000,"pvp_mpcost":7},{"required_level":6,"mpcost":15,"explanationid":21,"spcost":1,"cd":10000,"explanationparams":["112","21","6"],"pvp_explanationparams":["70","13","6"],"pvp_explanationid":39,"pvp_cd":12000,"pvp_mpcost":8},{"required_level":11,"mpcost":18,"explanationid":21,"spcost":1,"cd":10000,"explanationparams":["116","42","6"],"pvp_explanationparams":["72","25","6"],"pvp_explanationid":39,"pvp_cd":12000,"pvp_mpcost":9},{"required_level":16,"mpcost":21,"explanationid":21,"spcost":1,"cd":10000,"explanationparams":["120","71","6"],"pvp_explanationparams":["75","42","6"],"pvp_explanationid":39,"pvp_cd":12000,"pvp_mpcost":11},{"required_level":21,"mpcost":23,"explanationid":21,"spcost":1,"cd":10000,"explanationparams":["124","105","6"],"pvp_explanationparams":["78","63","6"],"pvp_explanationid":39,"pvp_cd":12000,"pvp_mpcost":12},{"required_level":26,"mpcost":26,"explanationid":22,"spcost":1,"cd":10000,"explanationparams":["149","331","25"],"pvp_explanationparams":["93","198","25"],"pvp_explanationid":40,"pvp_cd":12000,"pvp_mpcost":14},{"required_level":31,"mpcost":29,"explanationid":22,"spcost":1,"cd":10000,"explanationparams":["153","407","25"],"pvp_explanationparams":["95","244","25"],"pvp_explanationid":40,"pvp_cd":12000,"pvp_mpcost":15},{"required_level":36,"mpcost":31,"explanationid":22,"spcost":1,"cd":10000,"explanationparams":["157","987","25"],"pvp_explanationparams":["98","592","25"],"pvp_explanationid":40,"pvp_cd":12000,"pvp_mpcost":16},{"required_level":41,"mpcost":34,"explanationid":22,"spcost":1,"cd":10000,"explanationparams":["161","2228","25"],"pvp_explanationparams":["101","1337","25"],"pvp_explanationid":40,"pvp_cd":12000,"pvp_mpcost":17},{"required_level":46,"mpcost":36,"explanationid":22,"spcost":1,"cd":10000,"explanationparams":["166","2888","25"],"pvp_explanationparams":["104","1733","25"],"pvp_explanationid":40,"pvp_cd":12000,"pvp_mpcost":19},{"required_level":51,"mpcost":39,"explanationid":22,"spcost":1,"cd":10000,"explanationparams":["247","5386","25"],"pvp_explanationparams":["119","2486","25"],"pvp_explanationid":40,"pvp_cd":12000,"pvp_mpcost":20},{"required_level":56,"mpcost":41,"explanationid":22,"spcost":1,"cd":10000,"explanationparams":["252","6312","25"],"pvp_explanationparams":["121","2913","25"],"pvp_explanationid":40,"pvp_cd":12000,"pvp_mpcost":21},{"required_level":61,"mpcost":44,"explanationid":22,"spcost":1,"cd":10000,"explanationparams":["258","7128","25"],"pvp_explanationparams":["124","3290","25"],"pvp_explanationid":40,"pvp_cd":12000,"pvp_mpcost":22},{"required_level":66,"mpcost":46,"explanationid":22,"spcost":1,"cd":10000,"explanationparams":["263","7456","25"],"pvp_explanationparams":["127","3441","25"],"pvp_explanationid":40,"pvp_cd":12000,"pvp_mpcost":24},{"required_level":71,"mpcost":49,"explanationid":22,"spcost":1,"cd":10000,"explanationparams":["269","7802","25"],"pvp_explanationparams":["129","3601","25"],"pvp_explanationid":40,"pvp_cd":12000,"pvp_mpcost":25},{"required_level":76,"mpcost":52,"explanationid":22,"spcost":1,"cd":10000,"explanationparams":["300","9348","25"],"pvp_explanationparams":["144","4314","25"],"pvp_explanationid":40,"pvp_cd":12000,"pvp_mpcost":26},{"required_level":81,"mpcost":54,"explanationid":22,"spcost":1,"cd":10000,"explanationparams":["306","9734","25"],"pvp_explanationparams":["147","4493","25"],"pvp_explanationid":40,"pvp_cd":12000,"pvp_mpcost":28},{"required_level":86,"mpcost":57,"explanationid":22,"spcost":1,"cd":10000,"explanationparams":["311","10140","25"],"pvp_explanationparams":["150","4680","25"],"pvp_explanationid":40,"pvp_cd":12000,"pvp_mpcost":29}],"image":"02","icon":4,"needweapon":[],"requires":[],"sp_requires":[0,0]},"1009":{"type":0,"nameid":4,"maxlevel":9,"levels":[{"required_level":12,"mpcost":13,"explanationid":23,"spcost":3,"cd":120000,"explanationparams":["12","50"],"pvp_explanationparams":["6","50"],"pvp_explanationid":23,"pvp_cd":60000,"pvp_mpcost":7},{"required_level":22,"mpcost":17,"explanationid":23,"spcost":1,"cd":120000,"explanationparams":["14","55"],"pvp_explanationparams":["6","55"],"pvp_explanationid":23,"pvp_cd":60000,"pvp_mpcost":9},{"required_level":32,"mpcost":20,"explanationid":23,"spcost":1,"cd":120000,"explanationparams":["16","60"],"pvp_explanationparams":["6","60"],"pvp_explanationid":23,"pvp_cd":60000,"pvp_mpcost":10},{"required_level":42,"mpcost":23,"explanationid":23,"spcost":1,"cd":120000,"explanationparams":["18","65"],"pvp_explanationparams":["6","65"],"pvp_explanationid":23,"pvp_cd":60000,"pvp_mpcost":12},{"required_level":52,"mpcost":26,"explanationid":23,"spcost":1,"cd":120000,"explanationparams":["20","70"],"pvp_explanationparams":["6","70"],"pvp_explanationid":23,"pvp_cd":60000,"pvp_mpcost":13},{"required_level":62,"mpcost":29,"explanationid":23,"spcost":1,"cd":120000,"explanationparams":["22","75"],"pvp_explanationparams":["6","75"],"pvp_explanationid":23,"pvp_cd":60000,"pvp_mpcost":15},{"required_level":72,"mpcost":32,"explanationid":23,"spcost":1,"cd":120000,"explanationparams":["24","80"],"pvp_explanationparams":["6","80"],"pvp_explanationid":23,"pvp_cd":60000,"pvp_mpcost":16},{"required_level":82,"mpcost":35,"explanationid":23,"spcost":1,"cd":120000,"explanationparams":["26","85"],"pvp_explanationparams":["6","85"],"pvp_explanationid":23,"pvp_cd":60000,"pvp_mpcost":18},{"required_level":92,"mpcost":38,"explanationid":23,"spcost":1,"cd":120000,"explanationparams":["28","90"],"pvp_explanationparams":["6","90"],"pvp_explanationid":23,"pvp_cd":60000,"pvp_mpcost":19}],"image":"02","icon":16,"needweapon":[],"requires":[],"sp_requires":[0,0]},"1013":{"type":1,"nameid":5,"maxlevel":5,"levels":[{"required_level":1,"mpcost":12,"explanationid":24,"spcost":0,"cd":6000,"explanationparams":["6"],"pvp_explanationparams":["6"],"pvp_explanationid":24,"pvp_cd":6000,"pvp_mpcost":7},{"required_level":11,"mpcost":15,"explanationid":24,"spcost":1,"cd":4800,"explanationparams":["4.8"],"pvp_explanationparams":["4.8"],"pvp_explanationid":24,"pvp_cd":4800,"pvp_mpcost":8},{"required_level":21,"mpcost":18,"explanationid":24,"spcost":1,"cd":3900,"explanationparams":["3.9"],"pvp_explanationparams":["3.9"],"pvp_explanationid":24,"pvp_cd":3900,"pvp_mpcost":10},{"required_level":31,"mpcost":21,"explanationid":24,"spcost":1,"cd":3200,"explanationparams":["3.2"],"pvp_explanationparams":["3.2"],"pvp_explanationid":24,"pvp_cd":3200,"pvp_mpcost":11},{"required_level":41,"mpcost":24,"explanationid":24,"spcost":1,"cd":2600,"explanationparams":["2.6"],"pvp_explanationparams":["2.6"],"pvp_explanationid":24,"pvp_cd":2600,"pvp_mpcost":13}],"image":"01","icon":4,"needweapon":[],"requires":[],"sp_requires":[0,0]},"1016":{"type":1,"nameid":6,"maxlevel":1,"levels":[{"required_level":4,"mpcost":13,"explanationid":25,"spcost":1,"cd":5000,"explanationparams":["150"],"pvp_explanationparams":["150"],"pvp_explanationid":25,"pvp_cd":6000,"pvp_mpcost":7}],"image":"01","icon":2,"needweapon":[],"requires":[],"sp_requires":[0,0]},"1017":{"type":1,"nameid":7,"maxlevel":1,"levels":[{"required_level":1,"mpcost":12,"explanationid":26,"spcost":0,"cd":0,"explanationparams":["50"],"pvp_explanationparams":["50"],"pvp_explanationid":26,"pvp_cd":0,"pvp_mpcost":7}],"image":"01","icon":0,"needweapon":[],"requires":[],"sp_requires":[0,0]},"1018":{"type":1,"nameid":8,"maxlevel":1,"levels":[{"required_level":8,"mpcost":13,"explanationid":27,"spcost":1,"cd":3000,"explanationparams":["150"],"pvp_explanationparams":["150"],"pvp_explanationid":27,"pvp_cd":3000,"pvp_mpcost":7}],"image":"01","icon":1,"needweapon":[],"requires":[],"sp_requires":[0,0]},"1019":{"type":1,"nameid":9,"maxlevel":1,"levels":[{"required_level":1,"mpcost":12,"explanationid":28,"spcost":0,"cd":3000,"explanationparams":["150"],"pvp_explanationparams":["150"],"pvp_explanationid":28,"pvp_cd":3000,"pvp_mpcost":7}],"image":"01","icon":3,"needweapon":[],"requires":[],"sp_requires":[0,0]},"1021":{"type":1,"nameid":10,"maxlevel":1,"levels":[{"required_level":6,"mpcost":13,"explanationid":29,"spcost":1,"cd":12000,"explanationparams":["150"],"pvp_explanationparams":["150"],"pvp_explanationid":29,"pvp_cd":16000,"pvp_mpcost":7}],"image":"01","icon":5,"needweapon":[],"requires":[],"sp_requires":[0,0]},"1023":{"type":1,"nameid":11,"maxlevel":5,"levels":[{"required_level":10,"mpcost":13,"explanationid":30,"spcost":1,"cd":20000,"explanationparams":["20"],"pvp_explanationparams":["20"],"pvp_explanationid":30,"pvp_cd":20000,"pvp_mpcost":7},{"required_level":20,"mpcost":16,"explanationid":30,"spcost":1,"cd":18000,"explanationparams":["18"],"pvp_explanationparams":["18"],"pvp_explanationid":30,"pvp_cd":18000,"pvp_mpcost":9},{"required_level":30,"mpcost":19,"explanationid":30,"spcost":1,"cd":16000,"explanationparams":["16"],"pvp_explanationparams":["16"],"pvp_explanationid":30,"pvp_cd":16000,"pvp_mpcost":10},{"required_level":40,"mpcost":22,"explanationid":30,"spcost":1,"cd":14000,"explanationparams":["14"],"pvp_explanationparams":["15"],"pvp_explanationid":30,"pvp_cd":15000,"pvp_mpcost":12},{"required_level":50,"mpcost":25,"explanationid":30,"spcost":1,"cd":12000,"explanationparams":["12"],"pvp_explanationparams":["14"],"pvp_explanationid":30,"pvp_cd":14000,"pvp_mpcost":13}],"image":"02","icon":8,"needweapon":[],"requires":[{"id":1013,"level":1}],"sp_requires":[0,0]},"1024":{"type":1,"nameid":12,"maxlevel":4,"levels":[{"required_level":14,"mpcost":14,"explanationid":31,"spcost":1,"cd":30000,"explanationparams":["30"],"pvp_explanationparams":["30"],"pvp_explanationid":31,"pvp_cd":30000,"pvp_mpcost":7},{"required_level":24,"mpcost":17,"explanationid":31,"spcost":1,"cd":26000,"explanationparams":["26"],"pvp_explanationparams":["26"],"pvp_explanationid":31,"pvp_cd":26000,"pvp_mpcost":9},{"required_level":34,"mpcost":20,"explanationid":31,"spcost":1,"cd":22000,"explanationparams":["22"],"pvp_explanationparams":["22"],"pvp_explanationid":31,"pvp_cd":22000,"pvp_mpcost":10},{"required_level":44,"mpcost":23,"explanationid":31,"spcost":1,"cd":18000,"explanationparams":["18"],"pvp_explanationparams":["18"],"pvp_explanationid":31,"pvp_cd":18000,"pvp_mpcost":12}],"image":"01","icon":7,"needweapon":[],"requires":[],"sp_requires":[0,0]},"1026":{"type":0,"nameid":13,"maxlevel":29,"levels":[{"required_level":1,"mpcost":12,"explanationid":32,"spcost":0,"cd":9000,"explanationparams":["68","3"],"pvp_explanationparams":["42","1"],"pvp_explanationid":32,"pvp_cd":10000,"pvp_mpcost":7},{"required_level":4,"mpcost":15,"explanationid":32,"spcost":1,"cd":9000,"explanationparams":["71","9"],"pvp_explanationparams":["45","2"],"pvp_explanationid":32,"pvp_cd":10000,"pvp_mpcost":8},{"required_level":7,"mpcost":17,"explanationid":32,"spcost":1,"cd":9000,"explanationparams":["75","17"],"pvp_explanationparams":["47","3"],"pvp_explanationid":32,"pvp_cd":10000,"pvp_mpcost":9},{"required_level":10,"mpcost":20,"explanationid":32,"spcost":1,"cd":9000,"explanationparams":["79","23"],"pvp_explanationparams":["49","5"],"pvp_explanationid":32,"pvp_cd":10000,"pvp_mpcost":10},{"required_level":13,"mpcost":22,"explanationid":32,"spcost":1,"cd":9000,"explanationparams":["82","33"],"pvp_explanationparams":["51","7"],"pvp_explanationid":32,"pvp_cd":10000,"pvp_mpcost":11},{"required_level":16,"mpcost":25,"explanationid":32,"spcost":1,"cd":9000,"explanationparams":["112","62"],"pvp_explanationparams":["70","12"],"pvp_explanationid":32,"pvp_cd":10000,"pvp_mpcost":13},{"required_level":19,"mpcost":27,"explanationid":32,"spcost":1,"cd":9000,"explanationparams":["116","74"],"pvp_explanationparams":["72","15"],"pvp_explanationid":32,"pvp_cd":10000,"pvp_mpcost":14},{"required_level":22,"mpcost":29,"explanationid":32,"spcost":1,"cd":9000,"explanationparams":["119","100"],"pvp_explanationparams":["75","20"],"pvp_explanationid":32,"pvp_cd":10000,"pvp_mpcost":15},{"required_level":25,"mpcost":32,"explanationid":32,"spcost":1,"cd":9000,"explanationparams":["123","257"],"pvp_explanationparams":["77","51"],"pvp_explanationid":32,"pvp_cd":10000,"pvp_mpcost":16},{"required_level":28,"mpcost":34,"explanationid":32,"spcost":1,"cd":9000,"explanationparams":["127","291"],"pvp_explanationparams":["79","58"],"pvp_explanationid":32,"pvp_cd":10000,"pvp_mpcost":18},{"required_level":31,"mpcost":37,"explanationid":32,"spcost":1,"cd":9000,"explanationparams":["157","420"],"pvp_explanationparams":["98","84"],"pvp_explanationid":32,"pvp_cd":10000,"pvp_mpcost":19},{"required_level":34,"mpcost":39,"explanationid":32,"spcost":1,"cd":9000,"explanationparams":["160","978"],"pvp_explanationparams":["100","196"],"pvp_explanationid":32,"pvp_cd":10000,"pvp_mpcost":20},{"required_level":37,"mpcost":41,"explanationid":32,"spcost":1,"cd":9000,"explanationparams":["164","1159"],"pvp_explanationparams":["103","232"],"pvp_explanationid":32,"pvp_cd":10000,"pvp_mpcost":21},{"required_level":40,"mpcost":43,"explanationid":32,"spcost":1,"cd":9000,"explanationparams":["168","1360"],"pvp_explanationparams":["105","272"],"pvp_explanationid":32,"pvp_cd":10000,"pvp_mpcost":22},{"required_level":43,"mpcost":46,"explanationid":32,"spcost":1,"cd":9000,"explanationparams":["171","2774"],"pvp_explanationparams":["107","555"],"pvp_explanationid":32,"pvp_cd":10000,"pvp_mpcost":23},{"required_level":46,"mpcost":49,"explanationid":32,"spcost":1,"cd":9000,"explanationparams":["201","4143"],"pvp_explanationparams":["126","829"],"pvp_explanationid":32,"pvp_cd":10000,"pvp_mpcost":25},{"required_level":49,"mpcost":51,"explanationid":32,"spcost":1,"cd":9000,"explanationparams":["205","4652"],"pvp_explanationparams":["128","930"],"pvp_explanationid":32,"pvp_cd":10000,"pvp_mpcost":26},{"required_level":52,"mpcost":53,"explanationid":32,"spcost":1,"cd":9000,"explanationparams":["209","5173"],"pvp_explanationparams":["130","1035"],"pvp_explanationid":32,"pvp_cd":10000,"pvp_mpcost":27},{"required_level":55,"mpcost":55,"explanationid":32,"spcost":1,"cd":9000,"explanationparams":["212","5703"],"pvp_explanationparams":["133","1141"],"pvp_explanationid":32,"pvp_cd":10000,"pvp_mpcost":28},{"required_level":58,"mpcost":58,"explanationid":32,"spcost":1,"cd":9000,"explanationparams":["216","6245"],"pvp_explanationparams":["135","1249"],"pvp_explanationid":32,"pvp_cd":10000,"pvp_mpcost":29},{"required_level":61,"mpcost":60,"explanationid":32,"spcost":1,"cd":9000,"explanationparams":["246","7989"],"pvp_explanationparams":["154","1598"],"pvp_explanationid":32,"pvp_cd":10000,"pvp_mpcost":31},{"required_level":64,"mpcost":63,"explanationid":32,"spcost":1,"cd":9000,"explanationparams":["249","8215"],"pvp_explanationparams":["156","1643"],"pvp_explanationid":32,"pvp_cd":10000,"pvp_mpcost":32},{"required_level":67,"mpcost":65,"explanationid":32,"spcost":1,"cd":9000,"explanationparams":["253","8450"],"pvp_explanationparams":["158","1690"],"pvp_explanationid":32,"pvp_cd":10000,"pvp_mpcost":33},{"required_level":70,"mpcost":68,"explanationid":32,"spcost":1,"cd":9000,"explanationparams":["257","8695"],"pvp_explanationparams":["160","1739"],"pvp_explanationid":32,"pvp_cd":10000,"pvp_mpcost":34},{"required_level":73,"mpcost":70,"explanationid":32,"spcost":1,"cd":9000,"explanationparams":["260","8950"],"pvp_explanationparams":["163","1790"],"pvp_explanationid":32,"pvp_cd":10000,"pvp_mpcost":35},{"required_level":76,"mpcost":73,"explanationid":32,"spcost":1,"cd":9000,"explanationparams":["290","10760"],"pvp_explanationparams":["182","2152"],"pvp_explanationid":32,"pvp_cd":10000,"pvp_mpcost":37},{"required_level":79,"mpcost":75,"explanationid":32,"spcost":1,"cd":9000,"explanationparams":["294","11084"],"pvp_explanationparams":["184","2217"],"pvp_explanationid":32,"pvp_cd":10000,"pvp_mpcost":38},{"required_level":82,"mpcost":77,"explanationid":32,"spcost":1,"cd":9000,"explanationparams":["298","11418"],"pvp_explanationparams":["186","2284"],"pvp_explanationid":32,"pvp_cd":10000,"pvp_mpcost":39},{"required_level":85,"mpcost":80,"explanationid":32,"spcost":1,"cd":9000,"explanationparams":["301","11765"],"pvp_explanationparams":["188","2353"],"pvp_explanationid":32,"pvp_cd":10000,"pvp_mpcost":40}],"image":"02","icon":17,"needweapon":[],"requires":[],"sp_requires":[0,0]},"1027":{"type":0,"nameid":14,"maxlevel":27,"levels":[{"required_level":8,"mpcost":13,"explanationid":33,"spcost":3,"cd":8000,"explanationparams":["108","22","6"],"pvp_explanationparams":["26","3","6"],"pvp_explanationid":41,"pvp_cd":13000,"pvp_mpcost":7},{"required_level":11,"mpcost":16,"explanationid":33,"spcost":1,"cd":8000,"explanationparams":["113","32","6"],"pvp_explanationparams":["27","5","6"],"pvp_explanationid":41,"pvp_cd":13000,"pvp_mpcost":8},{"required_level":14,"mpcost":18,"explanationid":33,"spcost":1,"cd":8000,"explanationparams":["118","41","6"],"pvp_explanationparams":["28","6","6"],"pvp_explanationid":41,"pvp_cd":13000,"pvp_mpcost":10},{"required_level":17,"mpcost":20,"explanationid":33,"spcost":1,"cd":8000,"explanationparams":["122","59","6"],"pvp_explanationparams":["29","9","6"],"pvp_explanationid":41,"pvp_cd":13000,"pvp_mpcost":11},{"required_level":20,"mpcost":23,"explanationid":33,"spcost":1,"cd":8000,"explanationparams":["127","70","6"],"pvp_explanationparams":["31","11","6"],"pvp_explanationid":41,"pvp_cd":13000,"pvp_mpcost":12},{"required_level":23,"mpcost":25,"explanationid":34,"spcost":1,"cd":8000,"explanationparams":["183","120","25"],"pvp_explanationparams":["44","18","25"],"pvp_explanationid":42,"pvp_cd":13000,"pvp_mpcost":13},{"required_level":26,"mpcost":28,"explanationid":34,"spcost":1,"cd":8000,"explanationparams":["188","311","25"],"pvp_explanationparams":["45","48","25"],"pvp_explanationid":42,"pvp_cd":13000,"pvp_mpcost":14},{"required_level":29,"mpcost":30,"explanationid":34,"spcost":1,"cd":8000,"explanationparams":["193","352","25"],"pvp_explanationparams":["46","54","25"],"pvp_explanationid":42,"pvp_cd":13000,"pvp_mpcost":16},{"required_level":32,"mpcost":33,"explanationid":34,"spcost":1,"cd":8000,"explanationparams":["197","395","25"],"pvp_explanationparams":["47","61","25"],"pvp_explanationid":42,"pvp_cd":13000,"pvp_mpcost":17},{"required_level":35,"mpcost":35,"explanationid":34,"spcost":1,"cd":8000,"explanationparams":["202","956","25"],"pvp_explanationparams":["49","147","25"],"pvp_explanationid":42,"pvp_cd":13000,"pvp_mpcost":18},{"required_level":38,"mpcost":37,"explanationid":34,"spcost":1,"cd":8000,"explanationparams":["336","1908","25"],"pvp_explanationparams":["62","226","25"],"pvp_explanationid":42,"pvp_cd":13000,"pvp_mpcost":19},{"required_level":41,"mpcost":40,"explanationid":34,"spcost":1,"cd":8000,"explanationparams":["342","3980","25"],"pvp_explanationparams":["63","471","25"],"pvp_explanationid":42,"pvp_cd":13000,"pvp_mpcost":20},{"required_level":44,"mpcost":42,"explanationid":34,"spcost":1,"cd":8000,"explanationparams":["348","4580","25"],"pvp_explanationparams":["64","542","25"],"pvp_explanationid":42,"pvp_cd":13000,"pvp_mpcost":21},{"required_level":47,"mpcost":44,"explanationid":34,"spcost":1,"cd":8000,"explanationparams":["354","5525","25"],"pvp_explanationparams":["65","654","25"],"pvp_explanationid":42,"pvp_cd":13000,"pvp_mpcost":23},{"required_level":50,"mpcost":47,"explanationid":34,"spcost":1,"cd":8000,"explanationparams":["360","6193","25"],"pvp_explanationparams":["67","733","25"],"pvp_explanationid":42,"pvp_cd":13000,"pvp_mpcost":24},{"required_level":53,"mpcost":49,"explanationid":34,"spcost":1,"cd":8000,"explanationparams":["433","8526","25"],"pvp_explanationparams":["80","1009","25"],"pvp_explanationid":42,"pvp_cd":13000,"pvp_mpcost":25},{"required_level":56,"mpcost":52,"explanationid":34,"spcost":1,"cd":8000,"explanationparams":["439","9401","25"],"pvp_explanationparams":["81","1112","25"],"pvp_explanationid":42,"pvp_cd":13000,"pvp_mpcost":26},{"required_level":59,"mpcost":54,"explanationid":34,"spcost":1,"cd":8000,"explanationparams":["446","10293","25"],"pvp_explanationparams":["82","1218","25"],"pvp_explanationid":42,"pvp_cd":13000,"pvp_mpcost":27},{"required_level":62,"mpcost":56,"explanationid":34,"spcost":1,"cd":8000,"explanationparams":["452","10764","25"],"pvp_explanationparams":["84","1274","25"],"pvp_explanationid":42,"pvp_cd":13000,"pvp_mpcost":29},{"required_level":65,"mpcost":59,"explanationid":34,"spcost":1,"cd":8000,"explanationparams":["458","11052","25"],"pvp_explanationparams":["85","1308","25"],"pvp_explanationid":42,"pvp_cd":13000,"pvp_mpcost":30},{"required_level":68,"mpcost":61,"explanationid":34,"spcost":1,"cd":8000,"explanationparams":["531","13590","25"],"pvp_explanationparams":["98","1608","25"],"pvp_explanationid":42,"pvp_cd":13000,"pvp_mpcost":31},{"required_level":71,"mpcost":64,"explanationid":34,"spcost":1,"cd":8000,"explanationparams":["537","13972","25"],"pvp_explanationparams":["99","1654","25"],"pvp_explanationid":42,"pvp_cd":13000,"pvp_mpcost":32},{"required_level":74,"mpcost":66,"explanationid":34,"spcost":1,"cd":8000,"explanationparams":["543","14370","25"],"pvp_explanationparams":["100","1701","25"],"pvp_explanationid":42,"pvp_cd":13000,"pvp_mpcost":33},{"required_level":77,"mpcost":68,"explanationid":34,"spcost":1,"cd":8000,"explanationparams":["549","14785","25"],"pvp_explanationparams":["102","1750","25"],"pvp_explanationid":42,"pvp_cd":13000,"pvp_mpcost":35},{"required_level":80,"mpcost":71,"explanationid":34,"spcost":1,"cd":8000,"explanationparams":["555","15215","25"],"pvp_explanationparams":["103","1801","25"],"pvp_explanationid":42,"pvp_cd":13000,"pvp_mpcost":36},{"required_level":83,"mpcost":73,"explanationid":34,"spcost":1,"cd":8000,"explanationparams":["629","18274","25"],"pvp_explanationparams":["116","2163","25"],"pvp_explanationid":42,"pvp_cd":13000,"pvp_mpcost":37},{"required_level":86,"mpcost":76,"explanationid":34,"spcost":1,"cd":8000,"explanationparams":["635","18821","25"],"pvp_explanationparams":["117","2227","25"],"pvp_explanationid":42,"pvp_cd":13000,"pvp_mpcost":38}],"image":"02","icon":18,"needweapon":[],"requires":[],"sp_requires":[0,0]},"1028":{"type":1,"nameid":15,"maxlevel":23,"levels":[{"required_level":8,"mpcost":13,"explanationid":35,"spcost":1,"cd":0,"explanationparams":["102","20"],"pvp_explanationparams":["32","1"],"pvp_explanationid":35,"pvp_cd":0,"pvp_mpcost":7},{"required_level":11,"mpcost":16,"explanationid":35,"spcost":1,"cd":0,"explanationparams":["106","33"],"pvp_explanationparams":["33","1"],"pvp_explanationid":35,"pvp_cd":0,"pvp_mpcost":8},{"required_level":14,"mpcost":18,"explanationid":35,"spcost":1,"cd":0,"explanationparams":["110","47"],"pvp_explanationparams":["35","2"],"pvp_explanationid":35,"pvp_cd":0,"pvp_mpcost":10},{"required_level":17,"mpcost":21,"explanationid":35,"spcost":1,"cd":0,"explanationparams":["115","72"],"pvp_explanationparams":["36","3"],"pvp_explanationid":35,"pvp_cd":0,"pvp_mpcost":11},{"required_level":20,"mpcost":23,"explanationid":35,"spcost":1,"cd":0,"explanationparams":["119","94"],"pvp_explanationparams":["37","4"],"pvp_explanationid":35,"pvp_cd":0,"pvp_mpcost":12},{"required_level":23,"mpcost":26,"explanationid":35,"spcost":1,"cd":0,"explanationparams":["141","141"],"pvp_explanationparams":["44","6"],"pvp_explanationid":35,"pvp_cd":0,"pvp_mpcost":13},{"required_level":26,"mpcost":28,"explanationid":35,"spcost":1,"cd":0,"explanationparams":["145","370"],"pvp_explanationparams":["45","15"],"pvp_explanationid":35,"pvp_cd":0,"pvp_mpcost":15},{"required_level":29,"mpcost":31,"explanationid":35,"spcost":1,"cd":0,"explanationparams":["149","442"],"pvp_explanationparams":["47","18"],"pvp_explanationid":35,"pvp_cd":0,"pvp_mpcost":16},{"required_level":32,"mpcost":33,"explanationid":35,"spcost":1,"cd":0,"explanationparams":["154","521"],"pvp_explanationparams":["48","21"],"pvp_explanationid":35,"pvp_cd":0,"pvp_mpcost":17},{"required_level":35,"mpcost":35,"explanationid":35,"spcost":1,"cd":0,"explanationparams":["158","1118"],"pvp_explanationparams":["49","45"],"pvp_explanationid":35,"pvp_cd":0,"pvp_mpcost":18},{"required_level":38,"mpcost":38,"explanationid":35,"spcost":1,"cd":0,"explanationparams":["180","1503"],"pvp_explanationparams":["56","60"],"pvp_explanationid":35,"pvp_cd":0,"pvp_mpcost":19},{"required_level":41,"mpcost":40,"explanationid":35,"spcost":1,"cd":0,"explanationparams":["184","3078"],"pvp_explanationparams":["58","123"],"pvp_explanationid":35,"pvp_cd":0,"pvp_mpcost":21},{"required_level":44,"mpcost":42,"explanationid":35,"spcost":1,"cd":0,"explanationparams":["188","3557"],"pvp_explanationparams":["59","142"],"pvp_explanationid":35,"pvp_cd":0,"pvp_mpcost":22},{"required_level":47,"mpcost":45,"explanationid":35,"spcost":1,"cd":0,"explanationparams":["193","4233"],"pvp_explanationparams":["60","169"],"pvp_explanationid":35,"pvp_cd":0,"pvp_mpcost":23},{"required_level":50,"mpcost":47,"explanationid":35,"spcost":1,"cd":0,"explanationparams":["197","4772"],"pvp_explanationparams":["62","191"],"pvp_explanationid":35,"pvp_cd":0,"pvp_mpcost":24},{"required_level":53,"mpcost":50,"explanationid":35,"spcost":1,"cd":0,"explanationparams":["219","5999"],"pvp_explanationparams":["68","240"],"pvp_explanationid":35,"pvp_cd":0,"pvp_mpcost":25},{"required_level":56,"mpcost":52,"explanationid":35,"spcost":1,"cd":0,"explanationparams":["223","6644"],"pvp_explanationparams":["70","266"],"pvp_explanationid":35,"pvp_cd":0,"pvp_mpcost":26},{"required_level":59,"mpcost":54,"explanationid":35,"spcost":1,"cd":0,"explanationparams":["227","7310"],"pvp_explanationparams":["71","292"],"pvp_explanationid":35,"pvp_cd":0,"pvp_mpcost":28},{"required_level":62,"mpcost":57,"explanationid":35,"spcost":1,"cd":0,"explanationparams":["232","7760"],"pvp_explanationparams":["72","310"],"pvp_explanationid":35,"pvp_cd":0,"pvp_mpcost":29},{"required_level":65,"mpcost":59,"explanationid":35,"spcost":1,"cd":0,"explanationparams":["236","8121"],"pvp_explanationparams":["74","325"],"pvp_explanationid":35,"pvp_cd":0,"pvp_mpcost":30},{"required_level":68,"mpcost":62,"explanationid":35,"spcost":1,"cd":0,"explanationparams":["258","9324"],"pvp_explanationparams":["81","373"],"pvp_explanationid":35,"pvp_cd":0,"pvp_mpcost":31},{"required_level":71,"mpcost":64,"explanationid":35,"spcost":1,"cd":0,"explanationparams":["262","9719"],"pvp_explanationparams":["82","389"],"pvp_explanationid":35,"pvp_cd":0,"pvp_mpcost":33},{"required_level":74,"mpcost":67,"explanationid":35,"spcost":1,"cd":0,"explanationparams":["266","10132"],"pvp_explanationparams":["83","405"],"pvp_explanationid":35,"pvp_cd":0,"pvp_mpcost":34}],"image":"02","icon":19,"needweapon":[],"requires":[],"sp_requires":[0,0]},"1029":{"type":1,"nameid":16,"maxlevel":9,"levels":[{"required_level":20,"mpcost":0,"explanationid":36,"spcost":1,"cd":0,"explanationparams":["HP","3"],"pvp_explanationparams":["HP","3"],"pvp_explanationid":36,"pvp_cd":0,"pvp_mpcost":0},{"required_level":30,"mpcost":0,"explanationid":36,"spcost":1,"cd":0,"explanationparams":["HP","6"],"pvp_explanationparams":["HP","6"],"pvp_explanationid":36,"pvp_cd":0,"pvp_mpcost":0},{"required_level":40,"mpcost":0,"explanationid":36,"spcost":1,"cd":0,"explanationparams":["HP","9"],"pvp_explanationparams":["HP","9"],"pvp_explanationid":36,"pvp_cd":0,"pvp_mpcost":0},{"required_level":50,"mpcost":0,"explanationid":36,"spcost":1,"cd":0,"explanationparams":["HP","12"],"pvp_explanationparams":["HP","12"],"pvp_explanationid":36,"pvp_cd":0,"pvp_mpcost":0},{"required_level":60,"mpcost":0,"explanationid":36,"spcost":1,"cd":0,"explanationparams":["HP","15"],"pvp_explanationparams":["HP","15"],"pvp_explanationid":36,"pvp_cd":0,"pvp_mpcost":0},{"required_level":70,"mpcost":0,"explanationid":36,"spcost":1,"cd":0,"explanationparams":["HP","18"],"pvp_explanationparams":["HP","18"],"pvp_explanationid":36,"pvp_cd":0,"pvp_mpcost":0},{"required_level":80,"mpcost":0,"explanationid":36,"spcost":1,"cd":0,"explanationparams":["HP","21"],"pvp_explanationparams":["HP","21"],"pvp_explanationid":36,"pvp_cd":0,"pvp_mpcost":0},{"required_level":90,"mpcost":0,"explanationid":36,"spcost":1,"cd":0,"explanationparams":["HP","24"],"pvp_explanationparams":["HP","24"],"pvp_explanationid":36,"pvp_cd":0,"pvp_mpcost":0},{"required_level":100,"mpcost":0,"explanationid":36,"spcost":1,"cd":0,"explanationparams":["HP","27"],"pvp_explanationparams":["HP","27"],"pvp_explanationid":36,"pvp_cd":0,"pvp_mpcost":0}],"image":"01","icon":6,"needweapon":[],"requires":[],"sp_requires":[0,0]},"1030":{"type":1,"nameid":17,"maxlevel":9,"levels":[{"required_level":20,"mpcost":0,"explanationid":36,"spcost":1,"cd":0,"explanationparams":["MP","3"],"pvp_explanationparams":["MP","3"],"pvp_explanationid":36,"pvp_cd":0,"pvp_mpcost":0},{"required_level":30,"mpcost":0,"explanationid":36,"spcost":1,"cd":0,"explanationparams":["MP","6"],"pvp_explanationparams":["MP","6"],"pvp_explanationid":36,"pvp_cd":0,"pvp_mpcost":0},{"required_level":40,"mpcost":0,"explanationid":36,"spcost":1,"cd":0,"explanationparams":["MP","9"],"pvp_explanationparams":["MP","9"],"pvp_explanationid":36,"pvp_cd":0,"pvp_mpcost":0},{"required_level":50,"mpcost":0,"explanationid":36,"spcost":1,"cd":0,"explanationparams":["MP","12"],"pvp_explanationparams":["MP","12"],"pvp_explanationid":36,"pvp_cd":0,"pvp_mpcost":0},{"required_level":60,"mpcost":0,"explanationid":36,"spcost":1,"cd":0,"explanationparams":["MP","15"],"pvp_explanationparams":["MP","15"],"pvp_explanationid":36,"pvp_cd":0,"pvp_mpcost":0},{"required_level":70,"mpcost":0,"explanationid":36,"spcost":1,"cd":0,"explanationparams":["MP","18"],"pvp_explanationparams":["MP","18"],"pvp_explanationid":36,"pvp_cd":0,"pvp_mpcost":0},{"required_level":80,"mpcost":0,"explanationid":36,"spcost":1,"cd":0,"explanationparams":["MP","21"],"pvp_explanationparams":["MP","21"],"pvp_explanationid":36,"pvp_cd":0,"pvp_mpcost":0},{"required_level":90,"mpcost":0,"explanationid":36,"spcost":1,"cd":0,"explanationparams":["MP","24"],"pvp_explanationparams":["MP","24"],"pvp_explanationid":36,"pvp_cd":0,"pvp_mpcost":0},{"required_level":100,"mpcost":0,"explanationid":36,"spcost":1,"cd":0,"explanationparams":["MP","27"],"pvp_explanationparams":["MP","27"],"pvp_explanationid":36,"pvp_cd":0,"pvp_mpcost":0}],"image":"01","icon":8,"needweapon":[],"requires":[],"sp_requires":[0,0]},"1031":{"type":1,"nameid":18,"maxlevel":8,"levels":[{"required_level":30,"mpcost":0,"explanationid":37,"spcost":1,"cd":0,"explanationparams":["MP","1.5"],"pvp_explanationparams":["MP","1.5"],"pvp_explanationid":37,"pvp_cd":0,"pvp_mpcost":0},{"required_level":40,"mpcost":0,"explanationid":37,"spcost":1,"cd":0,"explanationparams":["MP","3"],"pvp_explanationparams":["MP","3"],"pvp_explanationid":37,"pvp_cd":0,"pvp_mpcost":0},{"required_level":50,"mpcost":0,"explanationid":37,"spcost":1,"cd":0,"explanationparams":["MP","4.5"],"pvp_explanationparams":["MP","4.5"],"pvp_explanationid":37,"pvp_cd":0,"pvp_mpcost":0},{"required_level":60,"mpcost":0,"explanationid":37,"spcost":1,"cd":0,"explanationparams":["MP","6"],"pvp_explanationparams":["MP","6"],"pvp_explanationid":37,"pvp_cd":0,"pvp_mpcost":0},{"required_level":70,"mpcost":0,"explanationid":37,"spcost":1,"cd":0,"explanationparams":["MP","7.5"],"pvp_explanationparams":["MP","7.5"],"pvp_explanationid":37,"pvp_cd":0,"pvp_mpcost":0},{"required_level":80,"mpcost":0,"explanationid":37,"spcost":1,"cd":0,"explanationparams":["MP","9"],"pvp_explanationparams":["MP","9"],"pvp_explanationid":37,"pvp_cd":0,"pvp_mpcost":0},{"required_level":90,"mpcost":0,"explanationid":37,"spcost":1,"cd":0,"explanationparams":["MP","10.5"],"pvp_explanationparams":["MP","10.5"],"pvp_explanationid":37,"pvp_cd":0,"pvp_mpcost":0},{"required_level":100,"mpcost":0,"explanationid":37,"spcost":1,"cd":0,"explanationparams":["MP","12"],"pvp_explanationparams":["MP","12"],"pvp_explanationid":37,"pvp_cd":0,"pvp_mpcost":0}],"image":"01","icon":9,"needweapon":[],"requires":[{"id":1030,"level":1}],"sp_requires":[0,0]}},"message":["Fury of the Owl","Twin Shot","Multi Shot","Willow Kick","Wisdom of the Owl","Tumble","Moon Kick","Spin Kick","Somersault Kick","Low Spin Kick","Pin Wheel","Power Tumble","Aerial Evasion","Piercing Shot","Magic Arrow","High Spin Kick","Health Bolster","Mental Fortitude","Attuned Mind","Shoots a pair of arrows. This skill can reach 3m further than your normal attacks. Effective on knocked down enemies. \\nAttack Power (per arrow): {0}% + {1}","Fires 7 arrows at enemies in a frontal cone. Enemies close to you take more damage.\\n#yPhysical Damage per Arrow: {0}%+{1}","#y[Physical Attack]#wSpin and kick nearby enemies with both feet. The last kick launches enemies into the air.\\n#yPhysical Damage: {0}% + {1}\\n\\n(The effect is enhanced at skill lv. {2}.)","#y[Physical Attack]#wSpin and kick nearby enemies with both feet. The last kick launches enemies into the air.\\n#yPhysical Damage: {0}% + {1}\\n\\nIncreases vortex effect range for enemies.\\nAdditional Damage: {2}%","Increases your party's Critical Chance by #y{1}%#w for #y{0} seconds#w.","Double-tap an arrow key or press #y[Shift]#w plus an arrow key to evade in that direction. Allows you to evade all attacks for a short time. \\n#yCooldown: {0} sec","Press the special attack button while jumping to kick an enemy as you descend. \\n#yPhysical Damage: {0}%","Press the special attack button while knocked down to push back an enemy with a roundhouse kick. \\n#yPhysical Damage: {0}%","Press the special attack button next to a stunned enemy to launch the enemy back with a kick. \\n#yPhysical Damage: {0}%","Press the special attack button near a knocked down enemy to perform a low roundhouse kick on them, slightly launching them. \\n#yPhysical Damage: {0}%","Press the attack button while knocked down to perform a whirling kick as you get back on your feet. \\n#yPhysical Damage: {0}%","Allows you to evade enemy attacks with #y[Tumble]#w even when paralyzed. \\n#yCooldown: {0} sec","When launched into the air, press the #y[Jump]#w key to land on your feet.\\n#yCooldown: {0} sec","Fires a quick arrow that pierces enemies. \\n#yAttack Power: {0}% + {1}","#y(Magic Arrow)\\n#wFires a magical arrow that creates a small explosion on contact.\\n#yMagic Damage: {0}% + {1}\\n\\n(The effect is enhanced at skill lv. {2}.)","#y(Magic Arrow)\\n#wFires a magical arrow that creates a small explosion on contact.\\n#yMagic Damage: {0}% + {1}\\n\\nPenetrates enemies, creating a line of small explosions.\\nAddtional Damage: {2}%","After a #y[Low Spin Kick]#w, press the special attack button to dash forward with a powerful kick.\\n#yAttack Power: {0}% + {1}","Increases max {0} by #y{1}%#w.","Increases your {0} recovery by #y{1}%#w every minute.","Increases the critical chance of yourself and allies by #y{0}%#w. \\nDuration: {1} sec","Spin and kick nearby enemies with both feet. The last kick launches enemies into the air.\\n#yPhysical Damage: {0}% + {1}\\n\\n(The effect is enhanced at skill lv. {2}.)","Spin and kick nearby enemies with both feet. The last kick launches enemies into the air.\\n#yPhysical Damage: {0}% + {1}\\n\\nIncreases the range and pulls enemies in.\\nAdditional Damage: {2}%","Fires a magical arrow that creates a small explosion on contact.\\n#yMagic Damage: {0}% + {1}\\n\\n(The effect is enhanced at skill lv. {2}.)","Fires a magical arrow that creates a small explosion on contact.\\n#yMagic Damage: {0}% + {1}\\n\\nPenetrates enemies, creating a line of small explosions.\\nAddtional Damage: {2}%"],"default_skills":[1017,1001,1026,1019,1008,1013]}